LICENSE
MANIFEST.in
README.md
setup.py
django_tilebundler.egg-info/PKG-INFO
django_tilebundler.egg-info/SOURCES.txt
django_tilebundler.egg-info/dependency_links.txt
django_tilebundler.egg-info/not-zip-safe
django_tilebundler.egg-info/requires.txt
django_tilebundler.egg-info/top_level.txt
fileservice/__init__.py
fileservice/api.py
fileservice/helpers.py
tilebundler/__init__.py
tilebundler/admin.py
tilebundler/api.py
tilebundler/helpers.py
tilebundler/models.py
tilebundler/tests.py
tilebundler/urls.py
tilebundler/views.py
tilebundler/static/tilesets/css/style.css
tilebundler/templates/tilesets/detail.html
tilebundler/templates/tilesets/index.html
tilebundler/templates/tilesets/results.html